splitnow/__init__.py
splitnow/client.py
splitnow/enums.py
splitnow/exceptions.py
splitnow/models.py
splitnow/py.typed
splitnow-1.0.0.dist-info/licenses/LICENSE
splitnow-1.0.0.dist-info/METADATA
splitnow-1.0.0.dist-info/WHEEL
splitnow-1.0.0.dist-info/top_level.txt
splitnow-1.0.0.dist-info/RECORD
