Metadata-Version: 2.4
Name: splitnow
Version: 1.0.0
Summary: Python SDK for the SplitNOW API - OTC Liquidity Aggregator
Author-email: "SplitOTC, Ltd" <support@splitnow.io>
License: UNLICENSED
Project-URL: Homepage, https://splitnow.io
Project-URL: Documentation, https://github.com/splitnow/python-sdk/blob/master/README.md
Project-URL: Repository, https://github.com/splitnow/python-sdk
Classifier: Development Status :: 4 - Beta
Classifier: Intended Audience :: Developers
Classifier: License :: OSI Approved :: The Unlicense (Unlicense)
Classifier: Operating System :: OS Independent
Classifier: Programming Language :: Python :: 3
Classifier: Programming Language :: Python :: 3.8
Classifier: Programming Language :: Python :: 3.9
Classifier: Programming Language :: Python :: 3.10
Classifier: Programming Language :: Python :: 3.11
Classifier: Programming Language :: Python :: 3.12
Classifier: Topic :: Software Development :: Libraries :: Python Modules
Classifier: Typing :: Typed
Requires-Python: >=3.8
License-File: LICENSE
Requires-Dist: requests>=2.25.0
Provides-Extra: dev
Requires-Dist: pytest>=7.0.0; extra == "dev"
Requires-Dist: python-dotenv>=0.19.0; extra == "dev"
Dynamic: license-file
